asset_tracking/__init__.py
asset_tracking/cli.py
asset_tracking/config.py
asset_tracking/core.py
asset_tracking/database/__init__.py
asset_tracking/database/operations.py
asset_tracking/database/schema.py
asset_tracking/models.py
asset_tracking/utils.py
asset_tracking-0.1.5.dist-info/LICENSE
asset_tracking-0.1.5.dist-info/METADATA
asset_tracking-0.1.5.dist-info/WHEEL
asset_tracking-0.1.5.dist-info/entry_points.txt
asset_tracking-0.1.5.dist-info/RECORD
